monitor_api_client-0.3.2.dist-info/licenses/LICENSE.txt
monitorapi/__init__.py
monitorapi/async_client.py
monitorapi/base_client.py
monitorapi/exceptions.py
monitorapi/py.typed
monitorapi/sync_client.py
monitor_api_client-0.3.2.dist-info/METADATA
monitor_api_client-0.3.2.dist-info/WHEEL
monitor_api_client-0.3.2.dist-info/top_level.txt
monitor_api_client-0.3.2.dist-info/RECORD
