Metadata-Version: 2.4
Name: monitor-api-client
Version: 0.3.2
Summary: Client for calling MonitorERP API
Author: rainerBoss
License: MIT License
Requires-Python: >=3.10
License-File: LICENSE.txt
Requires-Dist: httpx>=0.28.1
Dynamic: license-file
